grit/__init__.py
grit/__main__.py
grit/dashboard.py
grit/folder.py
grit/grafana.py
grit/grit.py
grit/helpers.py
grit/row.py
grit/stack.py
grit/utilities.py
grit/variation.py
noroutine_grit-0.0.8.dist-info/LICENSE
noroutine_grit-0.0.8.dist-info/METADATA
noroutine_grit-0.0.8.dist-info/WHEEL
noroutine_grit-0.0.8.dist-info/top_level.txt
noroutine_grit-0.0.8.dist-info/RECORD
