Metadata-Version: 2.1
Name: noroutine-grit
Version: 0.0.8
Summary: Grid Toolkit for Grafana
Home-page: https://github.com/noroutine/grit
Author: Oleksii Khilkevych
Author-email: oleksiy@noroutine.me
Maintainer: Noroutine GmbH
Maintainer-email: info@noroutine.me
License: MIT
Keywords: grafana,grafanalib,generator
Classifier: Programming Language :: Python :: 3
Classifier: License :: OSI Approved :: MIT License
Classifier: Operating System :: OS Independent
Requires-Python: >=3.9, <4
License-File: LICENSE
Requires-Dist: attrs
Requires-Dist: grafanalib
Requires-Dist: pydantic
Requires-Dist: pydantic-argparse
Requires-Dist: python-decouple
Requires-Dist: python-dotenv
Requires-Dist: PyYAML
Requires-Dist: requests
